{
  "924": {
    "item_entry": 924
  },
  "925": {
    "item_entry": 925
  },
  "926": {
    "item_entry": 926
  },
  "927": {
    "item_entry": 927
  },
  "928": {
    "item_entry": 928
  },
  "929": {
    "item_entry": 929
  },
  "930": {
    "item_entry": 930
  },
  "931": {
    "item_entry": 931
  },
  "932": {
    "item_entry": 932
  },
  "933": {
    "item_entry": 933
  },
  "934": {
    "item_entry": 934
  },
  "935": {
    "item_entry": 935
  },
  "1128": {
    "item_entry": 1128
  },
  "1129": {
    "item_entry": 1129
  },
  "1130": {
    "item_entry": 1130
  }
}
